{
  "main": {
    "name": "NICOLAS C.",
    "image": "image.jpg",
    "bio": "Hello, I'm Nicolas",
    "resumeDownload": "#",
    "social": [
      {
        "name": "linkedin",
        "url": "https://www.youtube.com/",
        "className": "fa fa-linkedin"
      },
      {
        "name": "github",
        "url": "https://www.youtube.com/",
        "className": "fa fa-github"
      },
      {
        "name": "email",
        "url": "https://www.youtube.com/",
        "className": "fa fa-envelope-o"
      }
    ]
  },
  "resume": {
    "skillmessage1": "Front End Proficiencies",
    "skillmessage2": "Back End Proficiencies",
    "skillmessage3": "DevOps/Other Applications ",
    "education": [
      {
        "school": "Gadjah Mada University",
        "degree": "Engineering Physics (Electrical & Electronic)",
        "graduated": "July 2021"
      }
    ],
    "certificates": [
      {
        "title": "UC Berkeley",
        "image": "ucbkproof.png",
        "description": "Completion of Coding Bootcamp"
      }
    ],
    "skills": [
      {
        "name": "HTML",
        "level": "90%"
      },
      {
        "name": "CSS",
        "level": "90%"
      },
      {
        "name": "JAVASCRIPT",
        "level": "70%"
      },
      {
        "name": "REACT",
        "level": "60%"
      },
      {
        "name": "MYSQL",
        "level": "80%"
      },
      {
        "name": "MONGOBD",
        "level": "80%"
      },
      {
        "name": "NODE",
        "level": "80%"
      }
    ]
  },
  "portfolio": {
    "projects": [
      {
        "id": 1,
        "title": "Movie Search App",
        "category": "Search a movie from the MovieDB API using JavaScript, React, React-Router, HTML, and CSS.",
        "image": "movieapp.png",
        "url": "https://nicolewallace09.github.io/react-movie-app/",
        "github": "https://github.com/nicolewallace09/react-movie-app"
      },
      {
        "id": 2,
        "title": "Student profiles",
        "category": "Search for students from an API and have the ability to view their information and add tags.",
        "image": "student.png",
        "url": "https://nicolewallace09.github.io/student-profiles/",
        "github": "https://github.com/nicolewallace09/student-profiles"
      },
      {
        "id": 3,
        "title": "Shopify Challenge",
        "category": "Save movie nominations from the OMDB API using JavaScript, React, React-Router, HTML, CSS, and Local Storage.",
        "image": "shoppies.png",
        "url": "https://nicolewallace09.github.io/the-shoppies/",
        "github": "https://github.com/nicolewallace09/the-shoppies"
      },
      {
        "id": 4,
        "title": "Travel Planner",
        "category": "A Travel Planner using JavaScript, jQuery, MateralizeCSS, CSS, HTML, and Local Storage, and HoteLook/SkyScanner APIs.",
        "image": "travelplanner.png",
        "url": "https://nicolewallace09.github.io/travel-planner/",
        "github": "https://github.com/nicolewallace09/travel-planner"
      },
      {
        "id": 5,
        "title": "Techly",
        "category": "CMS-style social networking site using MySql (Sequelize), Passport, Handlebars,js, Express.js, JavaScript, HTML, CSS and MVC paradigm.",
        "image": "techlyapp.png",
        "url": "https://techly.herokuapp.com/",
        "github": "https://github.com/nicolewallace09/techly"
      },
      {
        "id": 6,
        "title": "Team Profile Generator",
        "category": "A back end app to generate your team profile using Node, Inquirer, and Node Filesystem. (No deployed website)",
        "image": "teamprofile.png",
        "url": "https://github.com/nicolewallace09/team-profile-generator",
        "github": "https://github.com/nicolewallace09/team-profile-generator"
      }
    ]
  }
}
